README
setup.py
django_sqlfixtables.egg-info/PKG-INFO
django_sqlfixtables.egg-info/SOURCES.txt
django_sqlfixtables.egg-info/dependency_links.txt
django_sqlfixtables.egg-info/top_level.txt
sqlfixtables/__init__.py
sqlfixtables/management/__init__.py
sqlfixtables/management/commands/__init__.py
sqlfixtables/management/commands/sqlfixtables.py