Metadata-Version: 1.1
Name: django-sqlfixtables
Version: 1.2
Summary: Management command for fixing tables after model changes
Home-page: http://github.com/seveas/django-sqlfixtables
Author: Dennis Kaarsemaker
Author-email: dennis@kaarsemaker.net
License: UNKNOWN
Platform: UNKNOWN
Classifier: Framework :: Django
Classifier: Intended Audience :: Developers
Classifier: Operating System :: OS Independent
Classifier: Topic :: Software Development
